task3/ram.sv
module ram #(
    parameter   ADDRESS_WIDTH = 9,
                DATA_WIDTH = 8
)(
    input   logic                       clk,
    input   logic                       wr_en,
    input   logic                       rd_en,
    input   logic   [ADDRESS_WIDTH-1:0] wr_addr,
    input   logic   [ADDRESS_WIDTH-1:0] rd_addr,
    input   logic   [DATA_WIDTH-1:0]    din,
    output  logic   [DATA_WIDTH-1:0]    dout
);

logic [DATA_WIDTH-1:0] ram_array [2**ADDRESS_WIDTH-1:0];


always_ff @(posedge clk) begin
    if(wr_en == 1'b1)
        ram_array[wr_addr] <= din;
    if(rd_en == 1'b1)
        // ouput is synchronous
        dout <= ram_array [rd_addr];
end

endmodule

task3/counter.sv
module counter #(
    parameter WIDTH = 9
)(
    // interface signals
    input   logic               clk,    // clock
    input   logic               rst,    // reset
    input   logic               en,     // counter enable
    input   logic   [WIDTH-1:0] incr,   // increment value
    output  logic   [WIDTH-1:0] count   // count output
);

always_ff @( posedge clk, posedge rst) 
    if (rst)    count <= {WIDTH{1'b0}};
    else  if (en)      
        count <= count + incr; // if enabled, count is incremented by incr

endmodule

task3/sigdelay.sv
module sigdelay #(
    parameter   A_WIDTH = 9,
                D_WIDTH = 8
)(
    // interface signals
    input   logic                   clk,    // clock
    input   logic                   rst,    // reset
    input   logic                   en,     // enable
    input   logic                   wr,     // write
    input   logic                   rd,     // read
    input   logic   [D_WIDTH-1:0]   offset,   // offset
    input   logic   [D_WIDTH-1:0]   incr,   // increment for addr counter
    input   logic   [A_WIDTH-1:0]   mic_signal,  // output data1
    output  logic   [A_WIDTH-1:0]   delayed_signal   // output data2
);

    logic   [A_WIDTH-1:0]           wr_address;    // interconnect wire1
    logic   [A_WIDTH-1:0]           rd_address;    // interconnect wire2

counter addCounter (
    .clk (clk),
    .rst (rst),
    .en (en),
    .incr (incr),
    .count (wr_address)
);

always_comb begin
        rd_address = wr_address - offset;
    end

ram sigRam (
    .clk (clk),
    .wr_en (wr),
    .wr_addr (wr_address),
    .din (mic_signal),
    .rd_en (rd),
    .rd_addr (rd_address),
    .dout (delayed_signal)
);

endmodule

task3/sigdelay.vcd
$version Generated by VerilatedVcd $end
$date Wed Nov  1 17:09:48 2023 $end
$timescale 1ps $end

 $scope module TOP $end
  $var wire  1 # clk $end
  $var wire  9 + delayed_signal [8:0] $end
  $var wire  1 % en $end
  $var wire  8 ) incr [7:0] $end
  $var wire  9 * mic_signal [8:0] $end
  $var wire  8 ( offset [7:0] $end
  $var wire  1 ' rd $end
  $var wire  1 $ rst $end
  $var wire  1 & wr $end
  $scope module sigdelay $end
   $var wire 32 1 A_WIDTH [31:0] $end
   $var wire 32 2 D_WIDTH [31:0] $end
   $var wire  1 # clk $end
   $var wire  9 + delayed_signal [8:0] $end
   $var wire  1 % en $end
   $var wire  8 ) incr [7:0] $end
   $var wire  9 * mic_signal [8:0] $end
   $var wire  8 ( offset [7:0] $end
   $var wire  1 ' rd $end
   $var wire  9 - rd_address [8:0] $end
   $var wire  1 $ rst $end
   $var wire  1 & wr $end
   $var wire  9 , wr_address [8:0] $end
   $scope module addCounter $end
    $var wire 32 1 WIDTH [31:0] $end
    $var wire  1 # clk $end
    $var wire  9 , count [8:0] $end
    $var wire  1 % en $end
    $var wire  9 . incr [8:0] $end
    $var wire  1 $ rst $end
   $upscope $end
   $scope module sigRam $end
    $var wire 32 1 ADDRESS_WIDTH [31:0] $end
    $var wire 32 2 DATA_WIDTH [31:0] $end
    $var wire  1 # clk $end
    $var wire  8 / din [7:0] $end
    $var wire  8 0 dout [7:0] $end
    $var wire  9 - rd_addr [8:0] $end
    $var wire  1 ' rd_en $end
    $var wire  9 , wr_addr [8:0] $end
    $var wire  1 & wr_en $end
   $upscope $end
  $upscope $end
 $upscope $end
$enddefinitions $end


#0
1#
0$
1%
1&
1'
b01000000 (
b00000001 )
b000000000 *
b000000000 +
b000000000 ,
b111000000 -
b000000001 .
b00000000 /
b00000000 0
b00000000000000000000000000001001 1
b00000000000000000000000000001000 2
#1
0#
#2
1#
b00110011 (
b001100111 *
b000000001 ,
b111001110 -
b01100111 /
#3
0#
#4
1#
b001100011 *
b000000010 ,
b111001111 -
b01100011 /
#5
0#
#6
1#
b001101101 *
b000000011 ,
b111010000 -
b01101101 /
#7
0#
#8
1#
b001100110 *
b000000100 ,
b111010001 -
b01100110 /
#9
0#
#10
1#
b001101101 *
b000000101 ,
b111010010 -
b01101101 /
#11
0#
#12
1#
b001100111 *
b000000110 ,
b111010011 -
b01100111 /
#13
0#
#14
1#
b001101001 *
b000000111 ,
b111010100 -
b01101001 /
#15
0#
#16
1#
b001100111 *
b000001000 ,
b111010101 -
b01100111 /
#17
0#
#18
1#
b001100100 *
b000001001 ,
b111010110 -
b01100100 /
#19
0#
#20
1#
b001101010 *
b000001010 ,
b111010111 -
b01101010 /
#21
0#
#22
1#
b001101001 *
b000001011 ,
b111011000 -
b01101001 /
#23
0#
#24
1#
b000001100 ,
b111011001 -
#25
0#
#26
1#
b001101100 *
b000001101 ,
b111011010 -
b01101100 /
#27
0#
#28
1#
b000001110 ,
b111011011 -
#29
0#
#30
1#
b001101000 *
b000001111 ,
b111011100 -
b01101000 /
#31
0#
#32
1#
b001100101 *
b000010000 ,
b111011101 -
b01100101 /
#33
0#
#34
1#
b001100111 *
b000010001 ,
b111011110 -
b01100111 /
#35
0#
#36
1#
b001100101 *
b000010010 ,
b111011111 -
b01100101 /
#37
0#
#38
1#
b001101000 *
b000010011 ,
b111100000 -
b01101000 /
#39
0#
#40
1#
b001100011 *
b000010100 ,
b111100001 -
b01100011 /
#41
0#
#42
1#
b001100110 *
b000010101 ,
b111100010 -
b01100110 /
#43
0#
#44
1#
b000010110 ,
b111100011 -
#45
0#
#46
1#
b001100100 *
b000010111 ,
b111100100 -
b01100100 /
#47
0#
#48
1#
b001100110 *
b000011000 ,
b111100101 -
b01100110 /
#49
0#
#50
1#
b001101001 *
b000011001 ,
b111100110 -
b01101001 /
#51
0#
#52
1#
b001101000 *
b000011010 ,
b111100111 -
b01101000 /
#53
0#
#54
1#
b001100101 *
b000011011 ,
b111101000 -
b01100101 /
#55
0#
#56
1#
b001101000 *
b000011100 ,
b111101001 -
b01101000 /
#57
0#
#58
1#
b001100101 *
b000011101 ,
b111101010 -
b01100101 /
#59
0#
#60
1#
b001101100 *
b000011110 ,
b111101011 -
b01101100 /
#61
0#
#62
1#
b001100110 *
b000011111 ,
b111101100 -
b01100110 /
#63
0#
#64
1#
b001100101 *
b000100000 ,
b111101101 -
b01100101 /
#65
0#
#66
1#
b001101001 *
b000100001 ,
b111101110 -
b01101001 /
#67
0#
#68
1#
b001100100 *
b000100010 ,
b111101111 -
b01100100 /
#69
0#
#70
1#
b001101000 *
b000100011 ,
b111110000 -
b01101000 /
#71
0#
#72
1#
b000100100 ,
b111110001 -
#73
0#
#74
1#
b001100110 *
b000100101 ,
b111110010 -
b01100110 /
#75
0#
#76
1#
b001101001 *
b000100110 ,
b111110011 -
b01101001 /
#77
0#
#78
1#
b001101010 *
b000100111 ,
b111110100 -
b01101010 /
#79
0#
#80
1#
b001100101 *
b000101000 ,
b111110101 -
b01100101 /
#81
0#
#82
1#
b001101100 *
b000101001 ,
b111110110 -
b01101100 /
#83
0#
#84
1#
b001101001 *
b000101010 ,
b111110111 -
b01101001 /
#85
0#
#86
1#
b001101000 *
b000101011 ,
b111111000 -
b01101000 /
#87
0#
#88
1#
b000101100 ,
b111111001 -
#89
0#
#90
1#
b001101001 *
b000101101 ,
b111111010 -
b01101001 /
#91
0#
#92
1#
b001100110 *
b000101110 ,
b111111011 -
b01100110 /
#93
0#
#94
1#
b001101000 *
b000101111 ,
b111111100 -
b01101000 /
#95
0#
#96
1#
b001101011 *
b000110000 ,
b111111101 -
b01101011 /
#97
0#
#98
1#
b001101010 *
b000110001 ,
b111111110 -
b01101010 /
#99
0#
#100
1#
b001101000 *
b000110010 ,
b111111111 -
b01101000 /
#101
0#
#102
1#
b001100101 *
b000110011 ,
b000000000 -
b01100101 /
#103
0#
#104
1#
b001101100 *
b000110100 ,
b000000001 -
b01101100 /
#105
0#
#106
1#
b001100111 +
b000110101 ,
b000000010 -
b01100111 0
#107
0#
#108
1#
b001101010 *
b001100011 +
b000110110 ,
b000000011 -
b01101010 /
b01100011 0
#109
0#
#110
1#
b001100110 *
b001101101 +
b000110111 ,
b000000100 -
b01100110 /
b01101101 0
#111
0#
#112
1#
b001101011 *
b001100110 +
b000111000 ,
b000000101 -
b01101011 /
b01100110 0
#113
0#
#114
1#
b001101110 *
b001101101 +
b000111001 ,
b000000110 -
b01101110 /
b01101101 0
#115
0#
#116
1#
b001101001 *
b001100111 +
b000111010 ,
b000000111 -
b01101001 /
b01100111 0
#117
0#
#118
1#
b001101001 +
b000111011 ,
b000001000 -
b01101001 0
#119
0#
#120
1#
b001100101 *
b001100111 +
b000111100 ,
b000001001 -
b01100101 /
b01100111 0
#121
0#
#122
1#
b001101000 *
b001100100 +
b000111101 ,
b000001010 -
b01101000 /
b01100100 0
#123
0#
#124
1#
b001101001 *
b001101010 +
b000111110 ,
b000001011 -
b01101001 /
b01101010 0
#125
0#
#126
1#
b001100001 *
b001101001 +
b000111111 ,
b000001100 -
b01100001 /
b01101001 0
#127
0#
#128
1#
b001100110 *
b001000000 ,
b000001101 -
b01100110 /
#129
0#
#130
1#
b001100100 *
b001101100 +
b001000001 ,
b000001110 -
b01100100 /
b01101100 0
#131
0#
#132
1#
b001101010 *
b001000010 ,
b000001111 -
b01101010 /
#133
0#
#134
1#
b001100110 *
b001101000 +
b001000011 ,
b000010000 -
b01100110 /
b01101000 0
#135
0#
#136
1#
b001101011 *
b001100101 +
b001000100 ,
b000010001 -
b01101011 /
b01100101 0
#137
0#
#138
1#
b001100101 *
b001100111 +
b001000101 ,
b000010010 -
b01100101 /
b01100111 0
#139
0#
#140
1#
b001101001 *
b001100101 +
b001000110 ,
b000010011 -
b01101001 /
b01100101 0
#141
0#
#142
1#
b001100111 *
b001101000 +
b001000111 ,
b000010100 -
b01100111 /
b01101000 0
#143
0#
#144
1#
b001100110 *
b001100011 +
b001001000 ,
b000010101 -
b01100110 /
b01100011 0
#145
0#
#146
1#
b001101000 *
b001100110 +
b001001001 ,
b000010110 -
b01101000 /
b01100110 0
#147
0#
#148
1#
b001101101 *
b001001010 ,
b000010111 -
b01101101 /
#149
0#
#150
1#
b001100011 *
b001100100 +
b001001011 ,
b000011000 -
b01100011 /
b01100100 0
#151
0#
#152
1#
b001100110 +
b001001100 ,
b000011001 -
b01100110 0
#153
0#
#154
1#
b001101001 *
b001101001 +
b001001101 ,
b000011010 -
b01101001 /
b01101001 0
#155
0#
#156
1#
b001100110 *
b001101000 +
b001001110 ,
b000011011 -
b01100110 /
b01101000 0
#157
0#
#158
1#
b001101010 *
b001100101 +
b001001111 ,
b000011100 -
b01101010 /
b01100101 0
#159
0#
#160
1#
b001101000 *
b001101000 +
b001010000 ,
b000011101 -
b01101000 /
b01101000 0
#161
0#
#162
1#
b001100101 +
b001010001 ,
b000011110 -
b01100101 0
#163
0#
#164
1#
b001101001 *
b001101100 +
b001010010 ,
b000011111 -
b01101001 /
b01101100 0
#165
0#
#166
1#
b001101000 *
b001100110 +
b001010011 ,
b000100000 -
b01101000 /
b01100110 0
#167
0#
#168
1#
b001100110 *
b001100101 +
b001010100 ,
b000100001 -
b01100110 /
b01100101 0
#169
0#
#170
1#
b001101001 *
b001101001 +
b001010101 ,
b000100010 -
b01101001 /
b01101001 0
#171
0#
#172
1#
b001100111 *
b001100100 +
b001010110 ,
b000100011 -
b01100111 /
b01100100 0
#173
0#
#174
1#
b001101010 *
b001101000 +
b001010111 ,
b000100100 -
b01101010 /
b01101000 0
#175
0#
#176
1#
b001101001 *
b001011000 ,
b000100101 -
b01101001 /
#177
0#
#178
1#
b001100100 *
b001100110 +
b001011001 ,
b000100110 -
b01100100 /
b01100110 0
#179
0#
#180
1#
b001101010 *
b001101001 +
b001011010 ,
b000100111 -
b01101010 /
b01101001 0
#181
0#
#182
1#
b001101010 +
b001011011 ,
b000101000 -
b01101010 0
#183
0#
#184
1#
b001100111 *
b001100101 +
b001011100 ,
b000101001 -
b01100111 /
b01100101 0
#185
0#
#186
1#
b001100110 *
b001101100 +
b001011101 ,
b000101010 -
b01100110 /
b01101100 0
#187
0#
#188
1#
b001101000 *
b001101001 +
b001011110 ,
b000101011 -
b01101000 /
b01101001 0
#189
0#
#190
1#
b001100101 *
b001101000 +
b001011111 ,
b000101100 -
b01100101 /
b01101000 0
#191
0#
#192
1#
b001101010 *
b001100000 ,
b000101101 -
b01101010 /
#193
0#
#194
1#
b001100100 *
b001101001 +
b001100001 ,
b000101110 -
b01100100 /
b01101001 0
#195
0#
#196
1#
b001100110 *
b001100110 +
b001100010 ,
b000101111 -
b01100110 /
b01100110 0
#197
0#
#198
1#
b001101011 *
b001101000 +
b001100011 ,
b000110000 -
b01101011 /
b01101000 0
#199
0#
#200
1#
b001100101 *
b001101011 +
b001100100 ,
b000110001 -
b01100101 /
b01101011 0
#201
0#
#202
1#
b001101001 *
b001101010 +
b001100101 ,
b000110010 -
b01101001 /
b01101010 0
#203
0#
#204
1#
b001101011 *
b001101000 +
b001100110 ,
b000110011 -
b01101011 /
b01101000 0
#205
0#
#206
1#
b001101010 *
b001100101 +
b001100111 ,
b000110100 -
b01101010 /
b01100101 0
#207
0#
#208
1#
b001101000 *
b001101100 +
b001101000 ,
b000110101 -
b01101000 /
b01101100 0
#209
0#
#210
1#
b001101110 *
b001101001 ,
b000110110 -
b01101110 /
#211
0#
#212
1#
b001101000 *
b001101010 +
b001101010 ,
b000110111 -
b01101000 /
b01101010 0
#213
0#
#214
1#
b001100110 +
b001101011 ,
b000111000 -
b01100110 0
#215
0#
#216
1#
b001100111 *
b001101011 +
b001101100 ,
b000111001 -
b01100111 /
b01101011 0
#217
0#
#218
1#
b001100100 *
b001101110 +
b001101101 ,
b000111010 -
b01100100 /
b01101110 0
#219
0#
#220
1#
b001100101 *
b001101001 +
b001101110 ,
b000111011 -
b01100101 /
b01101001 0
#221
0#
#222
1#
b001100111 *
b001101111 ,
b000111100 -
b01100111 /
#223
0#
#224
1#
b001101100 *
b001100101 +
b001110000 ,
b000111101 -
b01101100 /
b01100101 0
#225
0#
#226
1#
b001101000 *
b001101000 +
b001110001 ,
b000111110 -
b01101000 /
b01101000 0
#227
0#
#228
1#
b001101001 *
b001101001 +
b001110010 ,
b000111111 -
b01101001 /
b01101001 0
#229
0#
#230
1#
b001101101 *
b001100001 +
b001110011 ,
b001000000 -
b01101101 /
b01100001 0
#231
0#
#232
1#
b001101010 *
b001100110 +
b001110100 ,
b001000001 -
b01101010 /
b01100110 0
#233
0#
#234
1#
b001101101 *
b001100100 +
b001110101 ,
b001000010 -
b01101101 /
b01100100 0
#235
0#
#236
1#
b001101111 *
b001101010 +
b001110110 ,
b001000011 -
b01101111 /
b01101010 0
#237
0#
#238
1#
b001101010 *
b001100110 +
b001110111 ,
b001000100 -
b01101010 /
b01100110 0
#239
0#
#240
1#
b001101000 *
b001101011 +
b001111000 ,
b001000101 -
b01101000 /
b01101011 0
#241
0#
#242
1#
b001101001 *
b001100101 +
b001111001 ,
b001000110 -
b01101001 /
b01100101 0
#243
0#
#244
1#
b001101001 +
b001111010 ,
b001000111 -
b01101001 0
#245
0#
#246
1#
b001101000 *
b001100111 +
b001111011 ,
b001001000 -
b01101000 /
b01100111 0
#247
0#
#248
1#
b001101001 *
b001100110 +
b001111100 ,
b001001001 -
b01101001 /
b01100110 0
#249
0#
#250
1#
b001100100 *
b001101000 +
b001111101 ,
b001001010 -
b01100100 /
b01101000 0
#251
0#
#252
1#
b001100111 *
b001101101 +
b001111110 ,
b001001011 -
b01100111 /
b01101101 0
#253
0#
#254
1#
b001101000 *
b001100011 +
b001111111 ,
b001001100 -
b01101000 /
b01100011 0
#255
0#
#256
1#
b001101010 *
b010000000 ,
b001001101 -
b01101010 /
#257
0#
#258
1#
b001100111 *
b001101001 +
b010000001 ,
b001001110 -
b01100111 /
b01101001 0
#259
0#
#260
1#
b001100100 *
b001100110 +
b010000010 ,
b001001111 -
b01100100 /
b01100110 0
#261
0#
#262
1#
b001101001 *
b001101010 +
b010000011 ,
b001010000 -
b01101001 /
b01101010 0
#263
0#
#264
1#
b001101011 *
b001101000 +
b010000100 ,
b001010001 -
b01101011 /
b01101000 0
#265
0#
#266
1#
b001100100 *
b010000101 ,
b001010010 -
b01100100 /
#267
0#
#268
1#
b001101001 *
b001101001 +
b010000110 ,
b001010011 -
b01101001 /
b01101001 0
#269
0#
#270
1#
b001100101 *
b001101000 +
b010000111 ,
b001010100 -
b01100101 /
b01101000 0
#271
0#
#272
1#
b001100110 +
b010001000 ,
b001010101 -
b01100110 0
#273
0#
#274
1#
b001101001 *
b001101001 +
b010001001 ,
b001010110 -
b01101001 /
b01101001 0
#275
0#
#276
1#
b001100100 *
b001100111 +
b010001010 ,
b001010111 -
b01100100 /
b01100111 0
#277
0#
#278
1#
b001101010 +
b010001011 ,
b001011000 -
b01101010 0
#279
0#
#280
1#
b001101001 *
b001101001 +
b010001100 ,
b001011001 -
b01101001 /
b01101001 0
#281
0#
#282
1#
b001100100 +
b010001101 ,
b001011010 -
b01100100 0
#283
0#
#284
1#
b001101011 *
b001101010 +
b010001110 ,
b001011011 -
b01101011 /
b01101010 0
#285
0#
#286
1#
b001101100 *
b010001111 ,
b001011100 -
b01101100 /
#287
0#
#288
1#
b001100100 *
b001100111 +
b010010000 ,
b001011101 -
b01100100 /
b01100111 0
#289
0#
#290
1#
b001101010 *
b001100110 +
b010010001 ,
b001011110 -
b01101010 /
b01100110 0
#291
0#
#292
1#
b001101000 *
b001101000 +
b010010010 ,
b001011111 -
b01101000 /
b01101000 0
#293
0#
#294
1#
b001101001 *
b001100101 +
b010010011 ,
b001100000 -
b01101001 /
b01100101 0
#295
0#
#296
1#
b001100111 *
b001101010 +
b010010100 ,
b001100001 -
b01100111 /
b01101010 0
#297
0#
#298
1#
b001100100 +
b010010101 ,
b001100010 -
b01100100 0
#299
0#
#300
1#
b001101010 *
b001100110 +
b010010110 ,
b001100011 -
b01101010 /
b01100110 0
#301
0#
#302
1#
b001101001 *
b001101011 +
b010010111 ,
b001100100 -
b01101001 /
b01101011 0
#303
0#
#304
1#
b001101011 *
b001100101 +
b010011000 ,
b001100101 -
b01101011 /
b01100101 0
#305
0#
#306
1#
b001101000 *
b001101001 +
b010011001 ,
b001100110 -
b01101000 /
b01101001 0
#307
0#
#308
1#
b001100110 *
b001101011 +
b010011010 ,
b001100111 -
b01100110 /
b01101011 0
#309
0#
#310
1#
b001101011 *
b001101010 +
b010011011 ,
b001101000 -
b01101011 /
b01101010 0
#311
0#
#312
1#
b001101000 *
b001101000 +
b010011100 ,
b001101001 -
b01101000 /
b01101000 0
#313
0#
#314
1#
b001100100 *
b001101110 +
b010011101 ,
b001101010 -
b01100100 /
b01101110 0
#315
0#
#316
1#
b001101001 *
b001101000 +
b010011110 ,
b001101011 -
b01101001 /
b01101000 0
#317
0#
#318
1#
b001101011 *
b010011111 ,
b001101100 -
b01101011 /
#319
0#
#320
1#
b001100110 *
b001100111 +
b010100000 ,
b001101101 -
b01100110 /
b01100111 0
#321
0#
#322
1#
b001100111 *
b001100100 +
b010100001 ,
b001101110 -
b01100111 /
b01100100 0
#323
0#
#324
1#
b001101010 *
b001100101 +
b010100010 ,
b001101111 -
b01101010 /
b01100101 0
#325
0#
#326
1#
b001100011 *
b001100111 +
b010100011 ,
b001110000 -
b01100011 /
b01100111 0
#327
0#
#328
1#
b001100101 *
b001101100 +
b010100100 ,
b001110001 -
b01100101 /
b01101100 0
#329
0#
#330
1#
b001100110 *
b001101000 +
b010100101 ,
b001110010 -
b01100110 /
b01101000 0
#331
0#
#332
1#
b001101001 +
b010100110 ,
b001110011 -
b01101001 0
#333
0#
#334
1#
b001100111 *
b001101101 +
b010100111 ,
b001110100 -
b01100111 /
b01101101 0
#335
0#
#336
1#
b001100101 *
b001101010 +
b010101000 ,
b001110101 -
b01100101 /
b01101010 0
#337
0#
#338
1#
b001101010 *
b001101101 +
b010101001 ,
b001110110 -
b01101010 /
b01101101 0
#339
0#
#340
1#
b001100101 *
b001101111 +
b010101010 ,
b001110111 -
b01100101 /
b01101111 0
#341
0#
#342
1#
b001101001 *
b001101010 +
b010101011 ,
b001111000 -
b01101001 /
b01101010 0
#343
0#
#344
1#
b001101000 +
b010101100 ,
b001111001 -
b01101000 0
#345
0#
#346
1#
b001100110 *
b001101001 +
b010101101 ,
b001111010 -
b01100110 /
b01101001 0
#347
0#
#348
1#
b001100100 *
b010101110 ,
b001111011 -
b01100100 /
#349
0#
#350
1#
b001100110 *
b001101000 +
b010101111 ,
b001111100 -
b01100110 /
b01101000 0
#351
0#
#352
1#
b001100111 *
b001101001 +
b010110000 ,
b001111101 -
b01100111 /
b01101001 0
#353
0#
#354
1#
b001100100 +
b010110001 ,
b001111110 -
b01100100 0
#355
0#
#356
1#
b001101001 *
b001100111 +
b010110010 ,
b001111111 -
b01101001 /
b01100111 0
#357
0#
#358
1#
b001100110 *
b001101000 +
b010110011 ,
b010000000 -
b01100110 /
b01101000 0
#359
0#
#360
1#
b001101000 *
b001101010 +
b010110100 ,
b010000001 -
b01101000 /
b01101010 0
#361
0#
#362
1#
b001100011 *
b001100111 +
b010110101 ,
b010000010 -
b01100011 /
b01100111 0
#363
0#
#364
1#
b001100101 *
b001100100 +
b010110110 ,
b010000011 -
b01100101 /
b01100100 0
#365
0#
#366
1#
b001101001 *
b001101001 +
b010110111 ,
b010000100 -
b01101001 /
b01101001 0
#367
0#
#368
1#
b001101000 *
b001101011 +
b010111000 ,
b010000101 -
b01101000 /
b01101011 0
#369
0#
#370
1#
b001100010 *
b001100100 +
b010111001 ,
b010000110 -
b01100010 /
b01100100 0
#371
0#
#372
1#
b001100101 *
b001101001 +
b010111010 ,
b010000111 -
b01100101 /
b01101001 0
#373
0#
#374
1#
b001100111 *
b001100101 +
b010111011 ,
b010001000 -
b01100111 /
b01100101 0
#375
0#
#376
1#
b010111100 ,
b010001001 -
#377
0#
#378
1#
b001100110 *
b001101001 +
b010111101 ,
b010001010 -
b01100110 /
b01101001 0
#379
0#
#380
1#
b001100111 *
b001100100 +
b010111110 ,
b010001011 -
b01100111 /
b01100100 0
#381
0#
#382
1#
b010111111 ,
b010001100 -
#383
0#
#384
1#
b001101001 *
b001101001 +
b011000000 ,
b010001101 -
b01101001 /
b01101001 0
#385
0#
#386
1#
b011000001 ,
b010001110 -
#387
0#
#388
1#
b001100101 *
b001101011 +
b011000010 ,
b010001111 -
b01100101 /
b01101011 0
#389
0#
#390
1#
b001101010 *
b001101100 +
b011000011 ,
b010010000 -
b01101010 /
b01101100 0
#391
0#
#392
1#
b00110010 (
b001101001 *
b001100100 +
b011000100 ,
b010010010 -
b01101001 /
b01100100 0
#393
0#
#394
1#
b001101010 *
b001101000 +
b011000101 ,
b010010011 -
b01101010 /
b01101000 0
#395
0#
#396
1#
b001101001 +
b011000110 ,
b010010100 -
b01101001 0
#397
0#
#398
1#
b001101001 *
b001100111 +
b011000111 ,
b010010101 -
b01101001 /
b01100111 0
#399
0#
#400
1#
b001101100 *
b011001000 ,
b010010110 -
b01101100 /
#401
0#
#402
1#
b001101011 *
b001101010 +
b011001001 ,
b010010111 -
b01101011 /
b01101010 0
#403
0#
#404
1#
b001101110 *
b001101001 +
b011001010 ,
b010011000 -
b01101110 /
b01101001 0
#405
0#
#406
1#
b001101011 +
b011001011 ,
b010011001 -
b01101011 0
#407
0#
#408
1#
b00110001 (
b001101100 *
b001101000 +
b011001100 ,
b010011011 -
b01101100 /
b01101000 0
#409
0#
#410
1#
b001101101 *
b001101011 +
b011001101 ,
b010011100 -
b01101101 /
b01101011 0
#411
0#
#412
1#
b001101010 *
b001101000 +
b011001110 ,
b010011101 -
b01101010 /
b01101000 0
#413
0#
#414
1#
b001101011 *
b001100100 +
b011001111 ,
b010011110 -
b01101011 /
b01100100 0
#415
0#
#416
1#
b001101010 *
b001101001 +
b011010000 ,
b010011111 -
b01101010 /
b01101001 0
#417
0#
#418
1#
b001101001 *
b001101011 +
b011010001 ,
b010100000 -
b01101001 /
b01101011 0
#419
0#
#420
1#
b00110000 (
b001100111 *
b001100110 +
b011010010 ,
b010100010 -
b01100111 /
b01100110 0
#421
0#
#422
1#
b001100100 *
b001101010 +
b011010011 ,
b010100011 -
b01100100 /
b01101010 0
#423
0#
#424
1#
b001100111 *
b001100011 +
b011010100 ,
b010100100 -
b01100111 /
b01100011 0
#425
0#
#426
1#
b001100110 *
b001100101 +
b011010101 ,
b010100101 -
b01100110 /
b01100101 0
#427
0#
#428
1#
b00101111 (
b001101000 *
b001100110 +
b011010110 ,
b010100111 -
b01101000 /
b01100110 0
#429
0#
#430
1#
b001101001 *
b001100111 +
b011010111 ,
b010101000 -
b01101001 /
b01100111 0
#431
0#
#432
1#
b001100001 *
b001100101 +
b011011000 ,
b010101001 -
b01100001 /
b01100101 0
#433
0#
#434
1#
b001100101 *
b001101010 +
b011011001 ,
b010101010 -
b01100101 /
b01101010 0
#435
0#
#436
1#
b00101110 (
b001100001 *
b001100101 +
b011011010 ,
b010101100 -
b01100001 /
b01100101 0
#437
0#
#438
1#
b001100011 *
b001101001 +
b011011011 ,
b010101101 -
b01100011 /
b01101001 0
#439
0#
#440
1#
b001100010 *
b001100110 +
b011011100 ,
b010101110 -
b01100010 /
b01100110 0
#441
0#
#442
1#
b001011110 *
b001100100 +
b011011101 ,
b010101111 -
b01011110 /
b01100100 0
#443
0#
#444
1#
b001100000 *
b001100110 +
b011011110 ,
b010110000 -
b01100000 /
b01100110 0
#445
0#
#446
1#
b001100001 *
b001100111 +
b011011111 ,
b010110001 -
b01100001 /
b01100111 0
#447
0#
#448
1#
b011100000 ,
b010110010 -
#449
0#
#450
1#
b001100110 *
b001101001 +
b011100001 ,
b010110011 -
b01100110 /
b01101001 0
#451
0#
#452
1#
b001100010 *
b001100110 +
b011100010 ,
b010110100 -
b01100010 /
b01100110 0
#453
0#
#454
1#
b001100001 *
b001101000 +
b011100011 ,
b010110101 -
b01100001 /
b01101000 0
#455
0#
#456
1#
b001100011 +
b011100100 ,
b010110110 -
b01100011 0
#457
0#
#458
1#
b001100011 *
b001100101 +
b011100101 ,
b010110111 -
b01100011 /
b01100101 0
#459
0#
#460
1#
b001100100 *
b001101001 +
b011100110 ,
b010111000 -
b01100100 /
b01101001 0
#461
0#
#462
1#
b001101000 +
b011100111 ,
b010111001 -
b01101000 0
#463
0#
#464
1#
b001100101 *
b001100010 +
b011101000 ,
b010111010 -
b01100101 /
b01100010 0
#465
0#
#466
1#
b001100011 *
b001100101 +
b011101001 ,
b010111011 -
b01100011 /
b01100101 0
#467
0#
#468
1#
b001100111 *
b001100111 +
b011101010 ,
b010111100 -
b01100111 /
b01100111 0
#469
0#
#470
1#
b001100011 *
b011101011 ,
b010111101 -
b01100011 /
#471
0#
#472
1#
b001100101 *
b001100110 +
b011101100 ,
b010111110 -
b01100101 /
b01100110 0
#473
0#
#474
1#
b001101000 *
b001100111 +
b011101101 ,
b010111111 -
b01101000 /
b01100111 0
#475
0#
#476
1#
b001100111 *
b011101110 ,
b011000000 -
b01100111 /
#477
0#
#478
1#
b001101001 +
b011101111 ,
b011000001 -
b01101001 0
#479
0#
#480
1#
b001101011 *
b011110000 ,
b011000010 -
b01101011 /
#481
0#
#482
1#
b001101000 *
b001100101 +
b011110001 ,
b011000011 -
b01101000 /
b01100101 0
#483
0#
#484
1#
b001100110 *
b001101010 +
b011110010 ,
b011000100 -
b01100110 /
b01101010 0
#485
0#
#486
1#
b001100111 *
b001101001 +
b011110011 ,
b011000101 -
b01100111 /
b01101001 0
#487
0#
#488
1#
b001101001 *
b001101010 +
b011110100 ,
b011000110 -
b01101001 /
b01101010 0
#489
0#
#490
1#
b001100110 *
b011110101 ,
b011000111 -
b01100110 /
#491
0#
#492
1#
b001101001 +
b011110110 ,
b011001000 -
b01101001 0
#493
0#
#494
1#
b001101000 *
b001101100 +
b011110111 ,
b011001001 -
b01101000 /
b01101100 0
#495
0#
#496
1#
b001100010 *
b001101011 +
b011111000 ,
b011001010 -
b01100010 /
b01101011 0
#497
0#
#498
1#
b001101110 +
b011111001 ,
b011001011 -
b01101110 0
#499
0#
#500
1#
b001100011 *
b011111010 ,
b011001100 -
b01100011 /
#501
0#
#502
1#
b001100101 *
b001101100 +
b011111011 ,
b011001101 -
b01100101 /
b01101100 0
#503
0#
#504
1#
b001100110 *
b001101101 +
b011111100 ,
b011001110 -
b01100110 /
b01101101 0
#505
0#
#506
1#
b001100111 *
b001101010 +
b011111101 ,
b011001111 -
b01100111 /
b01101010 0
#507
0#
#508
1#
b001100110 *
b001101011 +
b011111110 ,
b011010000 -
b01100110 /
b01101011 0
#509
0#
#510
1#
b001100100 *
b001101010 +
b011111111 ,
b011010001 -
b01100100 /
b01101010 0
#511
0#
#512
1#
b001100111 *
b001101001 +
b100000000 ,
b011010010 -
b01100111 /
b01101001 0
#513
0#
#514
1#
b001100111 +
b100000001 ,
b011010011 -
b01100111 0
#515
0#
#516
1#
b001100100 +
b100000010 ,
b011010100 -
b01100100 0
#517
0#
#518
1#
b001100111 +
b100000011 ,
b011010101 -
b01100111 0
#519
0#
#520
1#
b001101000 *
b001100110 +
b100000100 ,
b011010110 -
b01101000 /
b01100110 0
#521
0#
#522
1#
b001100110 *
b001101000 +
b100000101 ,
b011010111 -
b01100110 /
b01101000 0
#523
0#
#524
1#
b001101000 *
b001101001 +
b100000110 ,
b011011000 -
b01101000 /
b01101001 0
#525
0#
